astrodonut/__init__.py
astrodonut/donut.py
astrodonut/donut_List.py
astrodonut/donut_exporter.py
astrodonut/utils.py
astrodonut-0.1.0.dist-info/licenses/LICENSE
astrodonut-0.1.0.dist-info/METADATA
astrodonut-0.1.0.dist-info/WHEEL
astrodonut-0.1.0.dist-info/top_level.txt
astrodonut-0.1.0.dist-info/RECORD
