Metadata-Version: 2.4
Name: astrodonut
Version: 0.1.0
Summary: Tool for generating synthetic elliptical ring structures
Author-email: Eaton Jon Heidegger <a12034363@unet.univie.ac.at>
License: MIT
Requires-Python: >=3.8
License-File: LICENSE
Requires-Dist: numpy>=1.21
Requires-Dist: astropy>=5.0
Dynamic: license-file
